[{"id": "prod-1b523578026a43fe9a2c8ee7359b8e0e", "hs6": "3506", "title": "3000677145", "buyer": "Department of Defence", "buyer_country": "AUS", "buyer_code": 36, "seller": "ESI ALPHATEC", "seller_country": "AUS", "seller_code": 36, "match": "contract", "cpv": "", "date": "2026-07-15", "value": null, "currency": null, "url": "https://www.tenders.gov.au/Cn/Show/1b523578026a43fe9a2c8ee7359b8e0e"}, {"id": "688349-2025", "hs6": "3506", "title": "Adhesives", "buyer": "Polska Grupa Górnicza S.A.", "buyer_country": "POL", "buyer_code": 616, "seller": "J.P.COVER Sp. z o.o.", "seller_country": "POL", "seller_code": 616, "match": "contract", "cpv": "24911200", "date": "2025-07-15", "value": 9276199.03, "currency": "PLN", "url": "https://ted.europa.eu/en/notice/688349-2025"}, {"id": "528314-2025", "hs6": "3506", "title": "Nuts", "buyer": "Polska Grupa Górnicza S.A.", "buyer_country": "POL", "buyer_code": 616, "seller": "PROGRESS ECO", "seller_country": "POL", "seller_code": 616, "match": "lot", "cpv": "24911200", "date": "2025-06-03", "value": 2416719.0, "currency": "PLN", "url": "https://ted.europa.eu/en/notice/528314-2025"}, {"id": "723893-2024", "hs6": "3506", "title": "Nuts", "buyer": "Polska Grupa Górnicza S.A.", "buyer_country": "POL", "buyer_code": 616, "seller": "ZDT Glimag Sp. z o.o.", "seller_country": "POL", "seller_code": 616, "match": "lot", "cpv": "24911200", "date": "2024-11-05", "value": 3410860.24, "currency": "PLN", "url": "https://ted.europa.eu/en/notice/723893-2024"}, {"id": "648186-2024", "hs6": "3506", "title": "Nuts", "buyer": "Polska Grupa Górnicza S.A.", "buyer_country": "POL", "buyer_code": 616, "seller": "Basta Barczyk i Wspólnicy sp. z o.o. Osiedle Piastów 56B 31-625 Kraków", "seller_country": "POL", "seller_code": 616, "match": "lot", "cpv": "24911200", "date": "2024-10-02", "value": 3523818.89, "currency": "PLN", "url": "https://ted.europa.eu/en/notice/648186-2024"}, {"id": "455561-2024", "hs6": "3506", "title": "Adhesives", "buyer": "Polska Grupa Górnicza S.A.", "buyer_country": "POL", "buyer_code": 616, "seller": "PW ADITECH ADRIAN ŚLOSORZ ul. Bławatków 6, 41-412 Mysłowice", "seller_country": "POL", "seller_code": 616, "match": "contract", "cpv": "24911200", "date": "2024-06-24", "value": 6684462.4, "currency": "PLN", "url": "https://ted.europa.eu/en/notice/455561-2024"}, {"id": "841906-2025", "hs6": "3506", "title": "Adhesives", "buyer": "Lubelski Węgiel Bogdanka S.A. w Bogdance", "buyer_country": "POL", "buyer_code": 616, "seller": "Minova Ekochem Spółka z ograniczoną odpowiedzialnością", "seller_country": "POL", "seller_code": 616, "match": "contract", "cpv": "24911200", "date": "2025-12-18", "value": 43246418.95, "currency": "PLN", "url": "https://ted.europa.eu/en/notice/841906-2025"}, {"id": "834911-2025", "hs6": "3506", "title": "Medical equipments, pharmaceuticals and personal care products", "buyer": "SPITALUL CLINIC JUDETEAN DE URGENTA SF.SPIRIDON IASI", "buyer_country": "ROU", "buyer_code": 642, "seller": "B.BRAUN MEDICAL SRL", "seller_country": "ROU", "seller_code": 642, "match": "lot", "cpv": "24911200", "date": "2025-12-16", "value": 108683397.36, "currency": "RON", "url": "https://ted.europa.eu/en/notice/834911-2025"}, {"id": "808847-2025", "hs6": "3506", "title": "Construction materials and associated items", "buyer": "SPITALUL JUDETEAN DE URGENTA VALCEA", "buyer_country": "ROU", "buyer_code": 642, "seller": "AS INDUSTRIAL", "seller_country": "ROU", "seller_code": 642, "match": "lot", "cpv": "24911200", "date": "2025-12-05", "value": 340425.02, "currency": "RON", "url": "https://ted.europa.eu/en/notice/808847-2025"}, {"id": "654510-2025", "hs6": "3506", "title": "Medical equipments, pharmaceuticals and personal care products", "buyer": "SPITALUL CLINIC JUDETEAN DE URGENTA SF.SPIRIDON IASI", "buyer_country": "ROU", "buyer_code": 642, "seller": "SMART MEDICAL SOLUTIONS S.R.L.", "seller_country": "ROU", "seller_code": 642, "match": "lot", "cpv": "24911200", "date": "2025-10-07", "value": 108145797.36, "currency": "RON", "url": "https://ted.europa.eu/en/notice/654510-2025"}, {"id": "596403-2025", "hs6": "3506", "title": "Construction materials and associated items", "buyer": "SPITALUL JUDETEAN DE URGENTA VALCEA", "buyer_country": "ROU", "buyer_code": 642, "seller": "AMP GRUP", "seller_country": "ROU", "seller_code": 642, "match": "lot", "cpv": "24911200", "date": "2025-09-12", "value": 134576.81, "currency": "RON", "url": "https://ted.europa.eu/en/notice/596403-2025"}, {"id": "590299-2025", "hs6": "3506", "title": "Construction materials and associated items", "buyer": "SPITALUL JUDETEAN DE URGENTA VALCEA", "buyer_country": "ROU", "buyer_code": 642, "seller": "AMP GRUP", "seller_country": "ROU", "seller_code": 642, "match": "lot", "cpv": "24911200", "date": "2025-09-10", "value": 134576.81, "currency": "RON", "url": "https://ted.europa.eu/en/notice/590299-2025"}, {"id": "488475-2025", "hs6": "3506", "title": "Adhesives", "buyer": "SPL M TAG", "buyer_country": "FRA", "buyer_code": 250, "seller": "SIP", "seller_country": "FRA", "seller_code": 250, "match": "contract", "cpv": "24911200", "date": "2025-07-25", "value": 2125000.0, "currency": "EUR", "url": "https://ted.europa.eu/en/notice/488475-2025"}, {"id": "343334-2025", "hs6": "3506", "title": "Construction materials and associated items", "buyer": "SPITALUL JUDETEAN DE URGENTA VALCEA", "buyer_country": "ROU", "buyer_code": 642, "seller": "AMP GRUP", "seller_country": "ROU", "seller_code": 642, "match": "lot", "cpv": "24911200", "date": "2025-05-28", "value": 108610.06, "currency": "RON", "url": "https://ted.europa.eu/en/notice/343334-2025"}, {"id": "252966-2025", "hs6": "3506", "title": "Adhesives", "buyer": "Kopalnia Soli Bochnia sp. z o. o.", "buyer_country": "POL", "buyer_code": 616, "seller": "MINOVA EKOCHEM Sp. zo. o.", "seller_country": "POL", "seller_code": 616, "match": "contract", "cpv": "24911200", "date": "2025-04-17", "value": 2297715.0, "currency": "PLN", "url": "https://ted.europa.eu/en/notice/252966-2025"}, {"id": "78270-2025", "hs6": "3506", "title": "Adhesives", "buyer": "Tisséo Voyageurs", "buyer_country": "FRA", "buyer_code": 250, "seller": "SIP", "seller_country": "FRA", "seller_code": 250, "match": "contract", "cpv": "24911200", "date": "2025-02-05", "value": 410000.0, "currency": "EUR", "url": "https://ted.europa.eu/en/notice/78270-2025"}, {"id": "79191-2025", "hs6": "3506", "title": "Sign materials", "buyer": "CA DE BETHUNE BRUAY ARTOIS LYS ROMANE", "buyer_country": "FRA", "buyer_code": 250, "seller": "REPROCOLOR", "seller_country": "FRA", "seller_code": 250, "match": "lot", "cpv": "24911200", "date": "2025-02-05", "value": 620000.0, "currency": "EUR", "url": "https://ted.europa.eu/en/notice/79191-2025"}, {"id": "33932-2025", "hs6": "3506", "title": "Adhesives", "buyer": "Ministère de la Défense", "buyer_country": "BEL", "buyer_code": 56, "seller": "Metalen Galler", "seller_country": "BEL", "seller_code": 56, "match": "contract", "cpv": "24911200", "date": "2025-01-17", "value": 1320000.0, "currency": "EUR", "url": "https://ted.europa.eu/en/notice/33932-2025"}, {"id": "747547-2024", "hs6": "3506", "title": "Construction materials and associated items", "buyer": "SPITALUL JUDETEAN DE URGENTA VALCEA", "buyer_country": "ROU", "buyer_code": 642, "seller": "AMP GRUP", "seller_country": "ROU", "seller_code": 642, "match": "lot", "cpv": "24911200", "date": "2024-12-06", "value": 67754.71, "currency": "RON", "url": "https://ted.europa.eu/en/notice/747547-2024"}, {"id": "623593-2024", "hs6": "3506", "title": "Adhesives", "buyer": "Societatea COMPLEXUL ENERGETIC OLTENIA SA", "buyer_country": "ROU", "buyer_code": 642, "seller": "ARTEGO", "seller_country": "ROU", "seller_code": 642, "match": "contract", "cpv": "24911200", "date": "2024-10-15", "value": 2435815.25, "currency": "RON", "url": "https://ted.europa.eu/en/notice/623593-2024"}, {"id": "546199-2024", "hs6": "3506", "title": "Fine and various chemical products", "buyer": "Jastrzębska Spółka Węglowa S.A. z siedzibą w Jastrzębiu-Zdroju, Zakład Wsparcia Produkcji", "buyer_country": "POL", "buyer_code": 616, "seller": "PHU MOTO-REM Barbara Kula", "seller_country": "POL", "seller_code": 616, "match": "lot", "cpv": "24911200", "date": "2024-09-11", "value": 5000000.0, "currency": "PLN", "url": "https://ted.europa.eu/en/notice/546199-2024"}, {"id": "452670-2024", "hs6": "3506", "title": "Adhesives", "buyer": "Metz Métropole", "buyer_country": "FRA", "buyer_code": 250, "seller": "SDAG ADHESIFS", "seller_country": "FRA", "seller_code": 250, "match": "contract", "cpv": "24911200", "date": "2024-07-26", "value": 220000.0, "currency": "EUR", "url": "https://ted.europa.eu/en/notice/452670-2024"}, {"id": "437340-2024", "hs6": "3506", "title": "Adhesives", "buyer": "Societatea COMPLEXUL ENERGETIC OLTENIA SA", "buyer_country": "ROU", "buyer_code": 642, "seller": "ARTEGO", "seller_country": "ROU", "seller_code": 642, "match": "contract", "cpv": "24911200", "date": "2024-07-22", "value": 1500079.9, "currency": "RON", "url": "https://ted.europa.eu/en/notice/437340-2024"}]