[{"id": "479513-2026", "hs6": "7009", "title": "Educational games", "buyer": "Belső-Pesti Tankerületi Központ", "buyer_country": "HUN", "buyer_code": 348, "seller": "Almus Pater Taneszköz- és Intézményellátó Zrt.", "seller_country": "HUN", "seller_code": 348, "match": "lot", "cpv": "39299300", "date": "2026-05-18", "value": 90562320.0, "currency": "HUF", "url": "https://ted.europa.eu/en/notice/479513-2026"}, {"id": "25080-2026", "hs6": "7009", "title": "Mechanical spare parts except engines and engine parts", "buyer": "Societatea de Transport Bucuresti STB SA.", "buyer_country": "ROU", "buyer_code": 642, "seller": "DAIMLER TRUCK & BUS ROMANIA", "seller_country": "ROU", "seller_code": 642, "match": "lot", "cpv": "39299300", "date": "2026-01-14", "value": 2525627.77, "currency": "RON", "url": "https://ted.europa.eu/en/notice/25080-2026"}, {"id": "538785-2025", "hs6": "7009", "title": "Mechanical spare parts except engines and engine parts", "buyer": "Societatea de Transport Bucuresti STB SA.", "buyer_country": "ROU", "buyer_code": 642, "seller": "DAIMLER TRUCK & BUS ROMANIA", "seller_country": "ROU", "seller_code": 642, "match": "lot", "cpv": "39299300", "date": "2025-08-19", "value": 1174163.82, "currency": "RON", "url": "https://ted.europa.eu/en/notice/538785-2025"}, {"id": "162449-2025", "hs6": "7009", "title": "Glass mirrors", "buyer": "JUDETUL ARGES", "buyer_country": "ROU", "buyer_code": 642, "seller": "EBLUE MARKETING SOLUTIONS", "seller_country": "ROU", "seller_code": 642, "match": "contract", "cpv": "39299300", "date": "2025-03-13", "value": 72150.0, "currency": "RON", "url": "https://ted.europa.eu/en/notice/162449-2025"}, {"id": "70360-2025", "hs6": "7009", "title": "Mechanical spare parts except engines and engine parts", "buyer": "Societatea de Transport Bucuresti STB SA.", "buyer_country": "ROU", "buyer_code": 642, "seller": "DAIMLER TRUCK & BUS ROMANIA", "seller_country": "ROU", "seller_code": 642, "match": "lot", "cpv": "39299300", "date": "2025-01-31", "value": 633288.7, "currency": "RON", "url": "https://ted.europa.eu/en/notice/70360-2025"}, {"id": "64920-2025", "hs6": "7009", "title": "Mechanical spare parts except engines and engine parts", "buyer": "Societatea de Transport Bucuresti STB SA.", "buyer_country": "ROU", "buyer_code": 642, "seller": "ALIAT AUTO", "seller_country": "ROU", "seller_code": 642, "match": "lot", "cpv": "39299300", "date": "2025-01-30", "value": 6070117.4, "currency": "RON", "url": "https://ted.europa.eu/en/notice/64920-2025"}]