[{"id": "715534-2025", "hs6": "3820", "title": "Anti-freezing preparations", "buyer": "MÁV Személyszállítási Zártkörűen Működő Részvénytársaság", "buyer_country": "HUN", "buyer_code": 348, "seller": "MOL-LUB Kenőanyag Gyártó Forgalmazó és Szolgáltató Kft.", "seller_country": "HUN", "seller_code": 348, "match": "contract", "cpv": "24951311", "date": "2025-06-23", "value": 103000000.0, "currency": "HUF", "url": "https://ted.europa.eu/en/notice/715534-2025"}, {"id": "248092-2025", "hs6": "3820", "title": "Anti-freezing preparations", "buyer": "GRAD ZAGREB", "buyer_country": "HRV", "buyer_code": 191, "seller": "C.I.A.K. d.o.o.", "seller_country": "HRV", "seller_code": 191, "match": "contract", "cpv": "24951311", "date": "2024-12-19", "value": 68155.0, "currency": "EUR", "url": "https://ted.europa.eu/en/notice/248092-2025"}, {"id": "191261-2025", "hs6": "3820", "title": "Motor oils", "buyer": "ΔΗΜΟΣ ΘΕΣΣΑΛΟΝΙΚΗΣ", "buyer_country": "GRC", "buyer_code": 300, "seller": "ΕΤΑΙΡΙΑ ΔΕΛΤΑ ΟΪΛ ΕΛΛΑΣ Α.Β.Ε.Ε.", "seller_country": "GRC", "seller_code": 300, "match": "lot", "cpv": "24951311", "date": "2024-12-11", "value": 239586.0, "currency": "EUR", "url": "https://ted.europa.eu/en/notice/191261-2025"}, {"id": "47766-2025", "hs6": "3820", "title": "De-icing agents", "buyer": "Mazowiecki Port Lotniczy Warszawa-Modlin Sp. z o.o.", "buyer_country": "POL", "buyer_code": 616, "seller": "UAB Airstiga", "seller_country": "LTU", "seller_code": 440, "match": "lot", "cpv": "24951311", "date": "2024-11-22", "value": 2919300.0, "currency": "PLN", "url": "https://ted.europa.eu/en/notice/47766-2025"}, {"id": "115517-2026", "hs6": "3820", "title": "Anti-freezing preparations", "buyer": "БУРГАСБУС ЕООД", "buyer_country": "BGR", "buyer_code": 100, "seller": "КРИС ТРЕЙД 2000 ЕООД", "seller_country": "BGR", "seller_code": 100, "match": "contract", "cpv": "24951311", "date": "2026-02-18", "value": 1575.0, "currency": "EUR", "url": "https://ted.europa.eu/en/notice/115517-2026"}, {"id": "661222-2025", "hs6": "3820", "title": "Anti-freezing preparations", "buyer": "SNTFC \"CFR CALATORI\" S.A.", "buyer_country": "ROU", "buyer_code": 642, "seller": "HBG PETROCHEMICALS", "seller_country": "ROU", "seller_code": 642, "match": "contract", "cpv": "24951311", "date": "2025-10-09", "value": 164700.0, "currency": "RON", "url": "https://ted.europa.eu/en/notice/661222-2025"}, {"id": "486375-2025", "hs6": "3820", "title": "Anti-freezing preparations", "buyer": "UNITATEA MILITARA 01357 BUCURESTI", "buyer_country": "ROU", "buyer_code": 642, "seller": "KYNITA", "seller_country": "ROU", "seller_code": 642, "match": "contract", "cpv": "24951311", "date": "2025-07-24", "value": 348673.8, "currency": "RON", "url": "https://ted.europa.eu/en/notice/486375-2025"}, {"id": "479985-2025", "hs6": "3820", "title": "Anti-freezing preparations", "buyer": "UNITATEA MILITARA 01357 BUCURESTI", "buyer_country": "ROU", "buyer_code": 642, "seller": "KYNITA", "seller_country": "ROU", "seller_code": 642, "match": "contract", "cpv": "24951311", "date": "2025-07-23", "value": 318593.2, "currency": "RON", "url": "https://ted.europa.eu/en/notice/479985-2025"}, {"id": "359813-2025", "hs6": "3820", "title": "Anti-freezing preparations", "buyer": "СТОЛИЧЕН АВТОТРАНСПОРТ ЕАД", "buyer_country": "BGR", "buyer_code": 100, "seller": "КМВ Лабс ООД", "seller_country": "BGR", "seller_code": 100, "match": "contract", "cpv": "24951311", "date": "2025-06-04", "value": 616760.0, "currency": "BGN", "url": "https://ted.europa.eu/en/notice/359813-2025"}, {"id": "145955-2025", "hs6": "3820", "title": "Motor oils", "buyer": "Ministerul Apararii Nationale - Unitatea Militara 01145", "buyer_country": "ROU", "buyer_code": 642, "seller": "KYNITA", "seller_country": "ROU", "seller_code": 642, "match": "lot", "cpv": "24951311", "date": "2025-03-06", "value": 1422578.7, "currency": "RON", "url": "https://ted.europa.eu/en/notice/145955-2025"}, {"id": "125814-2025", "hs6": "3820", "title": "Anti-freezing preparations", "buyer": "SNTFC \"CFR CALATORI\" S.A.", "buyer_country": "ROU", "buyer_code": 642, "seller": "HBG PETROCHEMICALS", "seller_country": "ROU", "seller_code": 642, "match": "contract", "cpv": "24951311", "date": "2025-02-25", "value": 82350.0, "currency": "RON", "url": "https://ted.europa.eu/en/notice/125814-2025"}, {"id": "117736-2025", "hs6": "3820", "title": "Anti-freezing preparations", "buyer": "SNTFC \"CFR CALATORI\" S.A.", "buyer_country": "ROU", "buyer_code": 642, "seller": "HBG PETROCHEMICALS", "seller_country": "ROU", "seller_code": 642, "match": "contract", "cpv": "24951311", "date": "2025-02-21", "value": 164700.0, "currency": "RON", "url": "https://ted.europa.eu/en/notice/117736-2025"}, {"id": "666483-2024", "hs6": "3820", "title": "Anti-freezing preparations", "buyer": "БУРГАСБУС ЕООД", "buyer_country": "BGR", "buyer_code": 100, "seller": "ШИКО АДВАНС ООД", "seller_country": "BGR", "seller_code": 100, "match": "contract", "cpv": "24951311", "date": "2024-11-04", "value": 28000.0, "currency": "BGN", "url": "https://ted.europa.eu/en/notice/666483-2024"}, {"id": "494496-2024", "hs6": "3820", "title": "Anti-freezing preparations", "buyer": "БУРГАСБУС ЕООД", "buyer_country": "BGR", "buyer_code": 100, "seller": "РОБОТЕКС ЕООД", "seller_country": "BGR", "seller_code": 100, "match": "contract", "cpv": "24951311", "date": "2024-08-19", "value": 9528.75, "currency": "BGN", "url": "https://ted.europa.eu/en/notice/494496-2024"}]