[{"id": "206987-2026", "title": "Miscellaneous food products", "buyer": "DIRECTIA GENERALA DE ASISTENTA SOCIALA SI PROTECTIA COPILULUI", "buyer_country": "ROU", "buyer_code": 642, "seller": "BLACK SEA EUROINVESTMENT", "seller_country": "ROU", "seller_code": 642, "match": "lot", "cpv": "15892100", "date": "2026-03-25", "value": 511886.29, "currency": "RON", "url": "https://ted.europa.eu/en/notice/206987-2026"}, {"id": "178385-2026", "title": "Miscellaneous food products", "buyer": "DIRECTIA GENERALA DE ASISTENTA SOCIALA SI PROTECTIA COPILULUI", "buyer_country": "ROU", "buyer_code": 642, "seller": "BLACK SEA EUROINVESTMENT", "seller_country": "ROU", "seller_code": 642, "match": "lot", "cpv": "15892100", "date": "2026-03-16", "value": 1023674.83, "currency": "RON", "url": "https://ted.europa.eu/en/notice/178385-2026"}]