[{"id": "prod-6634a3ef5e0144bd86c61e3944c5cf62", "hs6": "3813", "title": "REF12144", "buyer": "Department of Climate Change, Energy, the Environment and Water", "buyer_country": "AUS", "buyer_code": 36, "seller": "[AUD] CONSILIUM AUSTRALIA PTY LI", "seller_country": "AUS", "seller_code": 36, "match": "contract", "cpv": "", "date": "2026-07-15", "value": null, "currency": null, "url": "https://www.tenders.gov.au/Cn/Show/6634a3ef5e0144bd86c61e3944c5cf62"}, {"id": "prod-adea4e6bd3df49a49d16aa175c5efb25", "hs6": "3813", "title": "3000677892", "buyer": "Department of Defence", "buyer_country": "AUS", "buyer_code": 36, "seller": "COUNTRY FIRE AUTHORITY", "seller_country": "AUS", "seller_code": 36, "match": "contract", "cpv": "", "date": "2026-07-15", "value": null, "currency": null, "url": "https://www.tenders.gov.au/Cn/Show/adea4e6bd3df49a49d16aa175c5efb25"}, {"id": "prod-f15d64079482455bada2e0ad1ef9302a", "hs6": "3813", "title": "3000677920", "buyer": "Department of Defence", "buyer_country": "AUS", "buyer_code": 36, "seller": "METROPOLITAN FIRE AND EMERGENCY SERVICES BOARD", "seller_country": "AUS", "seller_code": 36, "match": "contract", "cpv": "", "date": "2026-07-15", "value": null, "currency": null, "url": "https://www.tenders.gov.au/Cn/Show/f15d64079482455bada2e0ad1ef9302a"}, {"id": "prod-aef520c1230d4896b57d53fe1a7aa211", "hs6": "3813", "title": "3000679762", "buyer": "Department of Defence", "buyer_country": "AUS", "buyer_code": 36, "seller": "TASMANIA FIRE SERVICE", "seller_country": "AUS", "seller_code": 36, "match": "contract", "cpv": "", "date": "2026-07-15", "value": null, "currency": null, "url": "https://www.tenders.gov.au/Cn/Show/aef520c1230d4896b57d53fe1a7aa211"}, {"id": "prod-e7e65c688ebc4b8f94afde8dfdea5fdb", "hs6": "3813", "title": "3000675502", "buyer": "Department of Defence", "buyer_country": "AUS", "buyer_code": 36, "seller": "FIRE ALARM MONITORING SERVICES SERVICES", "seller_country": "AUS", "seller_code": 36, "match": "contract", "cpv": "", "date": "2026-07-13", "value": null, "currency": null, "url": "https://www.tenders.gov.au/Cn/Show/e7e65c688ebc4b8f94afde8dfdea5fdb"}, {"id": "prod-15f6ce61b4084441b4525c7fa4a41946", "hs6": "3813", "title": "4610005130", "buyer": "Department of Defence", "buyer_country": "AUS", "buyer_code": 36, "seller": "ROMTECK GRID PTY LTD", "seller_country": "AUS", "seller_code": 36, "match": "contract", "cpv": "", "date": "2026-07-13", "value": null, "currency": null, "url": "https://www.tenders.gov.au/Cn/Show/15f6ce61b4084441b4525c7fa4a41946"}, {"id": "prod-858b596e70ea4e66b8f3523bde4efc89", "hs6": "3813", "title": "4610005159", "buyer": "Department of Defence", "buyer_country": "AUS", "buyer_code": 36, "seller": "JOHNSON CONTROLS AUSTRALIA PTY LTD", "seller_country": "AUS", "seller_code": 36, "match": "contract", "cpv": "", "date": "2026-07-13", "value": null, "currency": null, "url": "https://www.tenders.gov.au/Cn/Show/858b596e70ea4e66b8f3523bde4efc89"}, {"id": "prod-043b7c6ee69a47df93a2e97105f6e2ee", "hs6": "3813", "title": "4610005158", "buyer": "Department of Defence", "buyer_country": "AUS", "buyer_code": 36, "seller": "SOUTH AUSTRALIAN METROPOLITAN FIRE SERVICE", "seller_country": "AUS", "seller_code": 36, "match": "contract", "cpv": "", "date": "2026-07-13", "value": null, "currency": null, "url": "https://www.tenders.gov.au/Cn/Show/043b7c6ee69a47df93a2e97105f6e2ee"}, {"id": "73197-2025", "hs6": "3813", "title": "Fire engines", "buyer": "Stadt Villingen-Schwenningen, Stabsstelle Zentrale Vergabestelle, Marktplatz 1, 78054 Villingen-Schwenningen, Deutschland", "buyer_country": "DEU", "buyer_code": 276, "seller": "Schmitz Feuerwehrtechnik", "seller_country": "DEU", "seller_code": 276, "match": "lot", "cpv": "24951230", "date": "2025-02-03", "value": 457183.5, "currency": "EUR", "url": "https://ted.europa.eu/en/notice/73197-2025"}, {"id": "34449-2025", "hs6": "3813", "title": "Fire engines", "buyer": "Amt Heider Umland", "buyer_country": "DEU", "buyer_code": 276, "seller": "Daimler Truck AG", "seller_country": "DEU", "seller_code": 276, "match": "lot", "cpv": "24951230", "date": "2025-01-17", "value": null, "currency": null, "url": "https://ted.europa.eu/en/notice/34449-2025"}, {"id": "12697-2025", "hs6": "3813", "title": "Fire engines", "buyer": "Amt Heider Umland", "buyer_country": "DEU", "buyer_code": 276, "seller": "Daimler Truck AG", "seller_country": "DEU", "seller_code": 276, "match": "lot", "cpv": "24951230", "date": "2025-01-09", "value": null, "currency": null, "url": "https://ted.europa.eu/en/notice/12697-2025"}, {"id": "759790-2024", "hs6": "3813", "title": "Firefighting vehicles", "buyer": "Stadtverwaltung Eisenach", "buyer_country": "DEU", "buyer_code": 276, "seller": "Rosenbauer Deutschland GmbH", "seller_country": "DEU", "seller_code": 276, "match": "lot", "cpv": "24951230", "date": "2024-12-12", "value": 804173.0, "currency": "EUR", "url": "https://ted.europa.eu/en/notice/759790-2024"}]