[{"id": "466546-2024", "hs6": "9406", "title": "Building materials", "buyer": "Skarb Państwa - 13 Wojskowy Oddział Gospodarczy (13 WOG)", "buyer_country": "POL", "buyer_code": 616, "seller": "\"METALZBYT-HURT\" Sp. z o.o.", "seller_country": "POL", "seller_code": 616, "match": "lot", "cpv": "39715000", "date": "2024-06-13", "value": 584832.56, "currency": "PLN", "url": "https://ted.europa.eu/en/notice/466546-2024"}, {"id": "427330-2024", "hs6": "9406", "title": "Heating equipment", "buyer": "HEP-Operator distribucijskog sustava d.o.o.", "buyer_country": "HRV", "buyer_code": 191, "seller": "Vodovod-Montaža d.o.o.", "seller_country": "HRV", "seller_code": 191, "match": "contract", "cpv": "39715000", "date": "2024-06-06", "value": 769489.49, "currency": "EUR", "url": "https://ted.europa.eu/en/notice/427330-2024"}, {"id": "432531-2024", "hs6": "9406", "title": "Plumbing equipment", "buyer": "Dundalk Institute of Technology_1155", "buyer_country": "IRL", "buyer_code": 372, "seller": "AEF Limited", "seller_country": "IRL", "seller_code": 372, "match": "contract", "cpv": "39715000", "date": "2023-09-01", "value": 50000.0, "currency": "EUR", "url": "https://ted.europa.eu/en/notice/432531-2024"}, {"id": "513146-2024", "hs6": "9406", "title": "Office and computing machinery, equipment and supplies except furniture and software packages", "buyer": "Landkreis Mecklenburgische Seenplatte", "buyer_country": "DEU", "buyer_code": 276, "seller": "CleanAgent Mehlfeld+Göring GmbH", "seller_country": "DEU", "seller_code": 276, "match": "lot", "cpv": "39715000", "date": "2024-08-27", "value": 1149495.17, "currency": "EUR", "url": "https://ted.europa.eu/en/notice/513146-2024"}, {"id": "513526-2024", "hs6": "9406", "title": "Central-heating equipment", "buyer": "Serviciul de Telecomunicatii Speciale", "buyer_country": "ROU", "buyer_code": 642, "seller": "Aqva Termo Sanit", "seller_country": "ROU", "seller_code": 642, "match": "contract", "cpv": "39715000", "date": "2024-08-27", "value": 1469740.0, "currency": "RON", "url": "https://ted.europa.eu/en/notice/513526-2024"}, {"id": "500109-2024", "hs6": "9406", "title": "Heating equipment", "buyer": "ОБЩИНА ПАЗАРДЖИК", "buyer_country": "BGR", "buyer_code": 100, "seller": "БГ ТЕРМ ООД", "seller_country": "BGR", "seller_code": 100, "match": "contract", "cpv": "39715000", "date": "2024-08-21", "value": 280810.0, "currency": "BGN", "url": "https://ted.europa.eu/en/notice/500109-2024"}, {"id": "489905-2024", "hs6": "9406", "title": "Heating equipment", "buyer": "Commune de Saint Christol Lez Alès", "buyer_country": "FRA", "buyer_code": 251, "seller": "Engie solutions", "seller_country": "FRA", "seller_code": 251, "match": "contract", "cpv": "39715000", "date": "2024-08-14", "value": 1211822.0, "currency": "EUR", "url": "https://ted.europa.eu/en/notice/489905-2024"}, {"id": "480158-2024", "hs6": "9406", "title": "Heating equipment", "buyer": "ОБЩИНА РУСЕ", "buyer_country": "BGR", "buyer_code": 100, "seller": "ПЕРФЕКТ ЕЛЕКТРА ООД", "seller_country": "BGR", "seller_code": 100, "match": "contract", "cpv": "39715000", "date": "2024-08-09", "value": 483450.0, "currency": "BGN", "url": "https://ted.europa.eu/en/notice/480158-2024"}, {"id": "478668-2024", "hs6": "9406", "title": "Kitchen equipment, household and domestic items and catering supplies", "buyer": "Landesamt für innere Verwaltung M-V, Abteilung Beschaffung/Dienstleistungen", "buyer_country": "DEU", "buyer_code": 276, "seller": "QUAMBUSCH PROTECT GmbH", "seller_country": "DEU", "seller_code": 276, "match": "lot", "cpv": "39715000", "date": "2024-08-08", "value": 97224.2, "currency": "EUR", "url": "https://ted.europa.eu/en/notice/478668-2024"}]