[{"id": "prod-7559149305014e1d9cc59c14aa5c1dc9", "hs6": "3923", "title": "3000690077", "buyer": "Department of Defence", "buyer_country": "AUS", "buyer_code": 36, "seller": "EQUANS AXIMA AUSTRALIA PTY LTD", "seller_country": "AUS", "seller_code": 36, "match": "contract", "cpv": "", "date": "2026-07-13", "value": null, "currency": null, "url": "https://www.tenders.gov.au/Cn/Show/7559149305014e1d9cc59c14aa5c1dc9"}, {"id": "546837-2024", "hs6": "3923", "title": "Test tubes", "buyer": "Ústav molekulární genetiky AV ČR, v. v. i.", "buyer_country": "CZE", "buyer_code": 203, "seller": "SARSTEDT spol. s r.o.", "seller_country": "CZE", "seller_code": 203, "match": "lot", "cpv": "19520000", "date": "2024-08-16", "value": 1825450.0, "currency": "CZK", "url": "https://ted.europa.eu/en/notice/546837-2024"}, {"id": "544201-2024", "hs6": "3923", "title": "Plastic products", "buyer": "Technologie hlavního města Prahy, a.s.", "buyer_country": "CZE", "buyer_code": 203, "seller": "ELKOPLAST CZ, s.r.o.", "seller_country": "CZE", "seller_code": 203, "match": "contract", "cpv": "19520000", "date": "2024-08-01", "value": 1750000.0, "currency": "CZK", "url": "https://ted.europa.eu/en/notice/544201-2024"}, {"id": "510875-2024", "hs6": "3923", "title": "Plastic products", "buyer": "Metro de Madrid, S.A.", "buyer_country": "ESP", "buyer_code": 724, "seller": "ESTUDIOS GRÁFICOS EUROPEOS, S.A", "seller_country": "ESP", "seller_code": 724, "match": "contract", "cpv": "19520000", "date": "2024-07-10", "value": null, "currency": "EUR", "url": "https://ted.europa.eu/en/notice/510875-2024"}, {"id": "450984-2024", "hs6": "3923", "title": "Compost boxes", "buyer": "Communauté d'agglomération Luberon Monts de Vaucluse", "buyer_country": "FRA", "buyer_code": 250, "seller": "ETS ROBIN SARL", "seller_country": "FRA", "seller_code": 250, "match": "lot", "cpv": "19520000", "date": "2024-06-21", "value": 404520.0, "currency": "EUR", "url": "https://ted.europa.eu/en/notice/450984-2024"}, {"id": "428667-2024", "hs6": "3923", "title": "Plastic products", "buyer": "Valstybės įmonė Ignalinos atominė elektrinė", "buyer_country": "LTU", "buyer_code": 440, "seller": "MB \"PRO GOV\"", "seller_country": "LTU", "seller_code": 440, "match": "contract", "cpv": "19520000", "date": "2024-06-18", "value": 99900.0, "currency": "EUR", "url": "https://ted.europa.eu/en/notice/428667-2024"}, {"id": "435604-2024", "hs6": "3923", "title": "Plastic products", "buyer": "Narodowy Instytut Kardiologii Stefana Kardynała Wyszyńskiego - Państwowy Instytut Badawczy", "buyer_country": "POL", "buyer_code": 616, "seller": "Intergos Sp. z o.o.", "seller_country": "POL", "seller_code": 616, "match": "contract", "cpv": "19520000", "date": "2024-06-17", "value": 202985.0, "currency": "PLN", "url": "https://ted.europa.eu/en/notice/435604-2024"}, {"id": "497077-2024", "hs6": "3923", "title": "Basic inorganic and organic chemicals", "buyer": "HUN-REN Balatoni Limnológiai Kutatóintézet", "buyer_country": "HUN", "buyer_code": 348, "seller": "Bio-Science Kereskedelmi és Szolgáltató Korlátolt Felelősségű Társaság", "seller_country": "HUN", "seller_code": 348, "match": "lot", "cpv": "19520000", "date": "2024-05-31", "value": 7428223.0, "currency": "HUF", "url": "https://ted.europa.eu/en/notice/497077-2024"}, {"id": "430964-2024", "hs6": "3923", "title": "Plastic products", "buyer": "Empresa de Transformación Agraria S.A.,S.M.E., M.P., (TRAGSA)", "buyer_country": "ESP", "buyer_code": 724, "seller": "MOLDBLADE S.L.", "seller_country": "ESP", "seller_code": 724, "match": "contract", "cpv": "19520000", "date": "2024-05-28", "value": 384025.59, "currency": "EUR", "url": "https://ted.europa.eu/en/notice/430964-2024"}, {"id": "441373-2024", "hs6": "3923", "title": "Plastic products", "buyer": "Krajská nemocnice Liberec, a.s.", "buyer_country": "CZE", "buyer_code": 203, "seller": "MATEO PACKING s.r.o.", "seller_country": "CZE", "seller_code": 203, "match": "contract", "cpv": "19520000", "date": "2024-05-21", "value": 2170585.4, "currency": "CZK", "url": "https://ted.europa.eu/en/notice/441373-2024"}, {"id": "434371-2024", "hs6": "3923", "title": "Chemical products", "buyer": "Magyar Agrár- és Élettudományi Egyetem", "buyer_country": "HUN", "buyer_code": 348, "seller": "VWR International Korlátolt Felelősségű Társaság", "seller_country": "HUN", "seller_code": 348, "match": "lot", "cpv": "19520000", "date": "2024-04-19", "value": 11914190.0, "currency": "HUF", "url": "https://ted.europa.eu/en/notice/434371-2024"}, {"id": "443499-2024", "hs6": "3923", "title": "Plastic products", "buyer": "Ostravská univerzita", "buyer_country": "CZE", "buyer_code": 203, "seller": "SIOT Trade s.r.o.", "seller_country": "CZE", "seller_code": 203, "match": "contract", "cpv": "19520000", "date": "2024-04-17", "value": 116052.72, "currency": "CZK", "url": "https://ted.europa.eu/en/notice/443499-2024"}, {"id": "461438-2024", "hs6": "3923", "title": "Plastic products", "buyer": "Česká pošta, s.p.", "buyer_country": "CZE", "buyer_code": 203, "seller": "PLASTON Liberec s.r.o.", "seller_country": "CZE", "seller_code": 203, "match": "contract", "cpv": "19520000", "date": "2021-01-25", "value": 125370.0, "currency": "CZK", "url": "https://ted.europa.eu/en/notice/461438-2024"}, {"id": "548172-2024", "hs6": "3923", "title": "Parts of railway or tramway locomotives or rolling stock; railways traffic-control equipment", "buyer": "Societatea de Transport Bucuresti STB SA.", "buyer_country": "ROU", "buyer_code": 642, "seller": "ANCA STEEL DISTRIBUTION", "seller_country": "ROU", "seller_code": 642, "match": "lot", "cpv": "19520000", "date": "2024-09-12", "value": 892926.0, "currency": "RON", "url": "https://ted.europa.eu/en/notice/548172-2024"}, {"id": "535963-2024", "hs6": "3923", "title": "Cleaning products", "buyer": "Narodowy Instytut Onkologii im. Marii Skłodowskiej-Curie - Państwowy Instytut Badawczy Oddział w Gliwicach", "buyer_country": "POL", "buyer_code": 616, "seller": "Henry Kruse Sp. z o.o.", "seller_country": "POL", "seller_code": 616, "match": "lot", "cpv": "19520000", "date": "2024-09-06", "value": 2502246.54, "currency": "PLN", "url": "https://ted.europa.eu/en/notice/535963-2024"}, {"id": "521319-2024", "hs6": "3923", "title": "Plastic products", "buyer": "Province de Liège", "buyer_country": "BEL", "buyer_code": 56, "seller": "SRL RE-UZ-BELGIUM", "seller_country": "BEL", "seller_code": 56, "match": "contract", "cpv": "19520000", "date": "2024-08-30", "value": null, "currency": null, "url": "https://ted.europa.eu/en/notice/521319-2024"}, {"id": "514223-2024", "hs6": "3923", "title": "Miscellaneous food products", "buyer": "WOJEWÓDZKI SZPITAL SPECJALISTYCZNY IM. BŁOGOSŁAWIONEGO KSIĘDZA JERZEGO POPIEŁUSZKI WE WŁOCŁAWKU", "buyer_country": "POL", "buyer_code": 616, "seller": "\"ABER\" Spółka z ograniczoną odpowiedzialnością", "seller_country": "POL", "seller_code": 616, "match": "lot", "cpv": "19520000", "date": "2024-08-27", "value": 1447940.87, "currency": "PLN", "url": "https://ted.europa.eu/en/notice/514223-2024"}, {"id": "506999-2024", "hs6": "3923", "title": "Plastic products", "buyer": "AB „Kelių priežiūra“", "buyer_country": "LTU", "buyer_code": 440, "seller": "Eccua UAB", "seller_country": "LTU", "seller_code": 440, "match": "contract", "cpv": "19520000", "date": "2024-08-23", "value": 300000.0, "currency": "EUR", "url": "https://ted.europa.eu/en/notice/506999-2024"}, {"id": "500576-2024", "hs6": "3923", "title": "Plastic products", "buyer": "Oesterreichische Nationalbank", "buyer_country": "AUT", "buyer_code": 40, "seller": "orfix International GmbH", "seller_country": "AUT", "seller_code": 40, "match": "contract", "cpv": "19520000", "date": "2024-08-21", "value": 954788.0, "currency": "EUR", "url": "https://ted.europa.eu/en/notice/500576-2024"}, {"id": "467775-2024", "hs6": "3923", "title": "Electrical supplies and accessories", "buyer": "4 Regionalna Baza Logistyczna we Wrocławiu", "buyer_country": "POL", "buyer_code": 616, "seller": "FUHP OLMOT Jerzy Olech", "seller_country": "POL", "seller_code": 616, "match": "lot", "cpv": "19520000", "date": "2024-08-02", "value": 80386.42, "currency": "PLN", "url": "https://ted.europa.eu/en/notice/467775-2024"}, {"id": "455943-2024", "hs6": "3923", "title": "Cleaning and polishing products", "buyer": "Samodzielny Publiczny Zakład Opieki Zdrowotnej - Szpital Uniwersytecki nr 2 im. dr Jana Biziela w Bydgoszczy", "buyer_country": "POL", "buyer_code": 616, "seller": "P.P.H.U. BARLON Bartłomiej Osiński", "seller_country": "POL", "seller_code": 616, "match": "lot", "cpv": "19520000", "date": "2024-07-30", "value": 550205.0, "currency": "PLN", "url": "https://ted.europa.eu/en/notice/455943-2024"}, {"id": "451075-2024", "hs6": "3923", "title": "Plastic products", "buyer": "Centrum experimentálnej medicíny Slovenskej akadémie vied, verejná výskumná inštitúcia", "buyer_country": "SVK", "buyer_code": 703, "seller": "Ing. Martin Fuchsberger - ECOMED", "seller_country": "SVK", "seller_code": 703, "match": "contract", "cpv": "19520000", "date": "2024-07-26", "value": null, "currency": null, "url": "https://ted.europa.eu/en/notice/451075-2024"}, {"id": "441854-2024", "hs6": "3923", "title": "Plastic products", "buyer": "Jastrzębska Spółka Węglowa S.A. z siedzibą w Jastrzębiu-Zdroju, Zakład Wsparcia Produkcji", "buyer_country": "POL", "buyer_code": 616, "seller": "MERITUM Sp. z o.o.", "seller_country": "POL", "seller_code": 616, "match": "contract", "cpv": "19520000", "date": "2024-07-23", "value": 4523941.23, "currency": "PLN", "url": "https://ted.europa.eu/en/notice/441854-2024"}]