[{"id": "134839-2026", "hs6": "6107", "title": "Clothing, footwear, luggage articles and accessories", "buyer": "Thüringer Ministerium für Justiz, Migration und Verbraucherschutz", "buyer_country": "DEU", "buyer_code": 276, "seller": "Bewernick GmbH Textilfabrik", "seller_country": "DEU", "seller_code": 276, "match": "lot", "cpv": "18312000", "date": "2026-02-26", "value": 290344.0, "currency": "EUR", "url": "https://ted.europa.eu/en/notice/134839-2026/html"}, {"id": "360691-2025", "hs6": "6107", "title": "Clothing, footwear, luggage articles and accessories", "buyer": "Thüringer Ministerium für Justiz, Migration und Verbraucherschutz", "buyer_country": "DEU", "buyer_code": 276, "seller": "Bewernick GmbH Textilfabrik", "seller_country": "DEU", "seller_code": 276, "match": "lot", "cpv": "18312000", "date": "2025-06-04", "value": 291200.0, "currency": "EUR", "url": "https://ted.europa.eu/en/notice/360691-2025/html"}]