[{"seller": "STEDYAN COM", "seller_country": "ROU", "seller_code": 642, "wins": 3, "last": "2024-11-22", "buyers": ["MINISTERUL APARARII - U.M. 02192", "Spitalul Clinic de Pneumoftiziologie Iasi"], "value": 2546593.96, "currency": "RON", "mixed": false, "url": "https://ted.europa.eu/en/notice/714952-2024"}, {"seller": "AVALUX-STAR SRL", "seller_country": "ROU", "seller_code": 642, "wins": 3, "last": "2024-09-10", "buyers": ["DIRECTIA GENERALA DE ASISTENTA SOCIALA SI PROTECTIA COPILULUI VASLUI"], "value": 585770.0, "currency": "RON", "mixed": false, "url": "https://ted.europa.eu/en/notice/543371-2024"}, {"seller": "OLYMEL FLAMINGO FOOD S.R.L.", "seller_country": "ROU", "seller_code": 642, "wins": 2, "last": "2024-10-30", "buyers": ["Directia Generala de Asistenta Sociala si Protectia Copilului Sector 2"], "value": 359612.86, "currency": "RON", "mixed": false, "url": "https://ted.europa.eu/en/notice/659197-2024"}, {"seller": "NORDIC IMPEX S.R.L.", "seller_country": "ROU", "seller_code": 642, "wins": 1, "last": "2024-10-23", "buyers": ["UNITATEA MILITARA 0663 DRAGASANI SCOALA MILITARA DE SUBOFITERI DE JANDARMI DRAGASANI"], "value": 1742877.22, "currency": "RON", "mixed": false, "url": "https://ted.europa.eu/en/notice/641734-2024"}, {"seller": "LEGUME FRUCTE COM S.R.L.", "seller_country": "ROU", "seller_code": 642, "wins": 1, "last": "2024-10-16", "buyers": ["DIRECTIA GENERALA DE ASISTENTA SOCIALA SI PROTECTIA COPILULUI SECTOR 6"], "value": 1716547.33, "currency": "RON", "mixed": false, "url": "https://ted.europa.eu/en/notice/627272-2024"}, {"seller": "BOBIX STAR S.R.L.", "seller_country": "ROU", "seller_code": 642, "wins": 1, "last": "2024-10-08", "buyers": ["UNITATEA MILITARA 0663 DRAGASANI SCOALA MILITARA DE SUBOFITERI DE JANDARMI DRAGASANI"], "value": 1276024.47, "currency": "RON", "mixed": false, "url": "https://ted.europa.eu/en/notice/604860-2024"}, {"seller": "COMPANY 94 PIRNAU SRL", "seller_country": "ROU", "seller_code": 642, "wins": 1, "last": "2024-10-01", "buyers": ["Scoala de Agenti de Politie '' VASILE LASCAR'' Campina"], "value": 3959681.02, "currency": "RON", "mixed": false, "url": "https://ted.europa.eu/en/notice/589373-2024"}, {"seller": "Apex Expert", "seller_country": "ROU", "seller_code": 642, "wins": 1, "last": "2024-09-12", "buyers": ["DIRECTIA GENERALA DE ASISTENTA SOCIALA SI PROTECTIA COPILULUI VASLUI"], "value": 138789.35, "currency": "RON", "mixed": false, "url": "https://ted.europa.eu/en/notice/548641-2024"}, {"seller": "JOHNSON & JOHNSON, S.A.", "seller_country": "ESP", "seller_code": 724, "wins": 1, "last": "2024-09-04", "buyers": ["HOSPITAL UNIVERSITARIO RAMÓN Y CAJAL"], "value": 84704.0, "currency": "EUR", "mixed": false, "url": "https://ted.europa.eu/en/notice/686739-2024"}, {"seller": "MATRA S.R.L.", "seller_country": "ROU", "seller_code": 642, "wins": 1, "last": "2024-08-29", "buyers": ["UNITATEA MILITARA 0663 DRAGASANI SCOALA MILITARA DE SUBOFITERI DE JANDARMI DRAGASANI"], "value": 1265620.07, "currency": "RON", "mixed": false, "url": "https://ted.europa.eu/en/notice/519323-2024"}, {"seller": "MASCAREIGNES DISTRIBUTION SAS", "seller_country": "FRA", "seller_code": 251, "wins": 1, "last": "2024-08-27", "buyers": ["Ville de Saint-Pierre"], "value": 43092000.0, "currency": "EUR", "mixed": false, "url": "https://ted.europa.eu/en/notice/513454-2024"}, {"seller": "PARHAN COM S.R.L.", "seller_country": "ROU", "seller_code": 642, "wins": 1, "last": "2024-08-02", "buyers": ["Scoala de Pregatire a Agentilor Politiei de Frontiera \"Avram Iancu\" Oradea"], "value": 511917.85, "currency": "RON", "mixed": false, "url": "https://ted.europa.eu/en/notice/466433-2024"}, {"seller": "Spółdzielnia Mleczarska Mlekovita", "seller_country": "POL", "seller_code": 616, "wins": 1, "last": "2024-07-31", "buyers": ["Samodzielny Publiczny Zakład Opieki Zdrowotnej - Szpital Uniwersytecki nr 2 im. dr Jana Biziela w Bydgoszczy"], "value": 2201716.51, "currency": "PLN", "mixed": false, "url": "https://ted.europa.eu/en/notice/459384-2024"}, {"seller": "VEGENAT HEATHCARE, S.L.U.", "seller_country": "ESP", "seller_code": 724, "wins": 1, "last": "2024-07-24", "buyers": ["HOSPITAL UNIVERSITARIO RAMÓN Y CAJAL"], "value": 232075.0, "currency": "EUR", "mixed": false, "url": "https://ted.europa.eu/en/notice/529764-2024"}, {"seller": "LACTATE NATURA", "seller_country": "ROU", "seller_code": 642, "wins": 1, "last": "2024-07-16", "buyers": ["MINISTERUL APARARII - UNITATEA MILITARA 02238 CHITILA"], "value": 21503.28, "currency": "RON", "mixed": false, "url": "https://ted.europa.eu/en/notice/425602-2024"}]