[{"seller": "GRANBIS", "seller_country": "ROU", "seller_code": 642, "wins": 4, "last": "2024-08-16", "buyers": ["DIRECTIA GENERALA ASISTENTA SOCIALA CONSTANTA"], "value": 3335470.0, "currency": "RON", "mixed": false, "url": "https://ted.europa.eu/en/notice/492096-2024"}, {"seller": "STEDYAN COM", "seller_country": "ROU", "seller_code": 642, "wins": 4, "last": "2024-08-14", "buyers": ["PENITENCIARUL BRAILA", "Spitalul Clinic de Pneumoftiziologie Iasi", "MINISTERUL APARARII - UNITATEA MILITARA 02497 PITESTI"], "value": 781782.0, "currency": "RON", "mixed": false, "url": "https://ted.europa.eu/en/notice/491053-2024"}, {"seller": "AMARIEI G. PETRU", "seller_country": "ROU", "seller_code": 642, "wins": 2, "last": "2024-08-09", "buyers": ["PENITENCIARUL DEVA"], "value": 720409.8, "currency": "RON", "mixed": false, "url": "https://ted.europa.eu/en/notice/481802-2024"}, {"seller": "OVIPAN", "seller_country": "ROU", "seller_code": 642, "wins": 2, "last": "2024-08-08", "buyers": ["PENITENCIARUL FOCSANI"], "value": 805488.6, "currency": "RON", "mixed": false, "url": "https://ted.europa.eu/en/notice/478176-2024"}, {"seller": "PRIORITAR IMPEX S.R.L.", "seller_country": "ROU", "seller_code": 642, "wins": 2, "last": "2024-08-07", "buyers": ["JUDETUL CARAS-SEVERIN", "JUDETUL SALAJ"], "value": 16954520.0, "currency": "RON", "mixed": false, "url": "https://ted.europa.eu/en/notice/476708-2024"}, {"seller": "S.C. AMA FRUCT CP S.R.L.", "seller_country": "ROU", "seller_code": 642, "wins": 2, "last": "2024-08-02", "buyers": ["Scoala de Pregatire a Agentilor Politiei de Frontiera \"Avram Iancu\" Oradea", "DIRECTIA DE ASISTENTA SOCIALA - PRIMARIA MUNICIPIULUI VASLUI"], "value": 644445.9199999999, "currency": "RON", "mixed": false, "url": "https://ted.europa.eu/en/notice/467178-2024"}, {"seller": "GELAS MEDIA", "seller_country": "ROU", "seller_code": 642, "wins": 2, "last": "2024-07-31", "buyers": ["DIRECTIA DE ASISTENTA SOCIALA - PRIMARIA MUNICIPIULUI VASLUI", "PENITENCIARUL BOTOSANI"], "value": 2190341.54, "currency": "RON", "mixed": false, "url": "https://ted.europa.eu/en/notice/461151-2024"}, {"seller": "FRUMOSUL DE VOINESTI DAMBOVITEAN COOPERATIVĂ AGRICOLĂ", "seller_country": "ROU", "seller_code": 642, "wins": 2, "last": "2024-07-24", "buyers": ["Consiliul Judetean Calarasi"], "value": 1.8199999999999998, "currency": "RON", "mixed": false, "url": "https://ted.europa.eu/en/notice/444029-2024"}, {"seller": "EUROGRUP BOGDAN", "seller_country": "ROU", "seller_code": 642, "wins": 2, "last": "2024-07-17", "buyers": ["PENITENCIARUL TG.JIU", "Penitenciarul Gherla"], "value": 478982.84, "currency": "RON", "mixed": false, "url": "https://ted.europa.eu/en/notice/428765-2024"}, {"seller": "MATRA S.R.L.", "seller_country": "ROU", "seller_code": 642, "wins": 1, "last": "2024-08-16", "buyers": ["Academia de Politie Alexandru Ioan Cuza Bucuresti"], "value": 10328420.0, "currency": "RON", "mixed": false, "url": "https://ted.europa.eu/en/notice/491761-2024"}, {"seller": "DORINA SUD SAS", "seller_country": "FRA", "seller_code": 251, "wins": 1, "last": "2024-08-16", "buyers": ["Métropole Nice Côte d'Azur (06)"], "value": 305690.0, "currency": "EUR", "mixed": false, "url": "https://ted.europa.eu/en/notice/492668-2024"}, {"seller": "AGROSEMCU", "seller_country": "ROU", "seller_code": 642, "wins": 1, "last": "2024-08-14", "buyers": ["JUDETUL SATU MARE"], "value": 316820.29, "currency": "RON", "mixed": false, "url": "https://ted.europa.eu/en/notice/490781-2024"}, {"seller": "LEGUME FRUCTE COM S.R.L.", "seller_country": "ROU", "seller_code": 642, "wins": 1, "last": "2024-08-12", "buyers": ["MINISTERUL APARARII - UNITATEA MILITARA 02497 PITESTI"], "value": 133579.75, "currency": "RON", "mixed": false, "url": "https://ted.europa.eu/en/notice/484348-2024"}, {"seller": "CARLAND S.R.L.", "seller_country": "ROU", "seller_code": 642, "wins": 1, "last": "2024-08-07", "buyers": ["MINISTERUL APARARII - UNITATEA MILITARA 02574"], "value": 1699441.8, "currency": "RON", "mixed": false, "url": "https://ted.europa.eu/en/notice/474487-2024"}, {"seller": "LECONFEX", "seller_country": "ROU", "seller_code": 642, "wins": 1, "last": "2024-08-06", "buyers": ["Penitenciarul cu Regim de Maxima Siguranta Arad"], "value": 1704924.6, "currency": "RON", "mixed": false, "url": "https://ted.europa.eu/en/notice/471294-2024"}, {"seller": "ADCON", "seller_country": "ROU", "seller_code": 642, "wins": 1, "last": "2024-08-05", "buyers": ["Spitalul Clinic de Pneumoftiziologie Victor Babes Craiova"], "value": 2229979.08, "currency": "RON", "mixed": false, "url": "https://ted.europa.eu/en/notice/468240-2024"}, {"seller": "PEDRA MEAT EXPRES SRL", "seller_country": "ROU", "seller_code": 642, "wins": 1, "last": "2024-08-05", "buyers": ["PENITENCIARUL CRAIOVA PELENDAVA"], "value": 327180.81, "currency": "RON", "mixed": false, "url": "https://ted.europa.eu/en/notice/470553-2024"}, {"seller": "SC IRINEL SRL", "seller_country": "ROU", "seller_code": 642, "wins": 1, "last": "2024-08-05", "buyers": ["PENITENCIARUL MIOVENI"], "value": 390236.0, "currency": "RON", "mixed": false, "url": "https://ted.europa.eu/en/notice/470578-2024"}, {"seller": "PARHAN COM S.R.L.", "seller_country": "ROU", "seller_code": 642, "wins": 1, "last": "2024-08-02", "buyers": ["Scoala de Pregatire a Agentilor Politiei de Frontiera \"Avram Iancu\" Oradea"], "value": 94072.5, "currency": "RON", "mixed": false, "url": "https://ted.europa.eu/en/notice/468124-2024"}, {"seller": "Spółdzielnia Mleczarska Mlekovita", "seller_country": "POL", "seller_code": 616, "wins": 1, "last": "2024-07-31", "buyers": ["Samodzielny Publiczny Zakład Opieki Zdrowotnej - Szpital Uniwersytecki nr 2 im. dr Jana Biziela w Bydgoszczy"], "value": 2201716.51, "currency": "PLN", "mixed": false, "url": "https://ted.europa.eu/en/notice/459384-2024"}, {"seller": "R & B COM S.R.L.", "seller_country": "ROU", "seller_code": 642, "wins": 1, "last": "2024-07-31", "buyers": ["JUDETUL SALAJ"], "value": 9428196.15, "currency": "RON", "mixed": false, "url": "https://ted.europa.eu/en/notice/461347-2024"}, {"seller": "POMURSKE MLEKARNE d.d.", "seller_country": "SVN", "seller_code": 705, "wins": 1, "last": "2024-07-29", "buyers": ["VIŠKI VRTCI"], "value": 571879.3, "currency": "EUR", "mixed": false, "url": "https://ted.europa.eu/en/notice/453788-2024"}, {"seller": "STEDYAN COM S.R.L.", "seller_country": "ROU", "seller_code": 642, "wins": 1, "last": "2024-07-26", "buyers": ["Spitalul Judetan de Urgenta \"Mavromati\" Botosani"], "value": 1635873.33, "currency": "RON", "mixed": false, "url": "https://ted.europa.eu/en/notice/449949-2024"}, {"seller": "SIGISMUND COM", "seller_country": "ROU", "seller_code": 642, "wins": 1, "last": "2024-07-26", "buyers": ["Penitenciarul Oradea"], "value": 1490257.04, "currency": "RON", "mixed": false, "url": "https://ted.europa.eu/en/notice/450647-2024"}, {"seller": "AMIA INVEST", "seller_country": "ROU", "seller_code": 642, "wins": 1, "last": "2024-07-26", "buyers": ["Spitalul Clinic de Pneumoftiziologie Iasi"], "value": 1374182.5, "currency": "RON", "mixed": false, "url": "https://ted.europa.eu/en/notice/452173-2024"}, {"seller": "OLYMEL FLAMINGO FOOD S.R.L.", "seller_country": "ROU", "seller_code": 642, "wins": 1, "last": "2024-07-24", "buyers": ["Directia Generala de Asistenta Sociala si Protectia Copilului Sector 2"], "value": 400570.0, "currency": "RON", "mixed": false, "url": "https://ted.europa.eu/en/notice/443041-2024"}, {"seller": "La Leul Com", "seller_country": "ROU", "seller_code": 642, "wins": 1, "last": "2024-07-16", "buyers": ["Directia Generala de Asistenta Sociala si Protectia Copilului Mehedinti"], "value": 1202460.4, "currency": "RON", "mixed": false, "url": "https://ted.europa.eu/en/notice/424154-2024"}, {"seller": "LACTATE NATURA", "seller_country": "ROU", "seller_code": 642, "wins": 1, "last": "2024-07-16", "buyers": ["MINISTERUL APARARII - UNITATEA MILITARA 02238 CHITILA"], "value": 21503.28, "currency": "RON", "mixed": false, "url": "https://ted.europa.eu/en/notice/425602-2024"}, {"seller": "ROMICS", "seller_country": "ROU", "seller_code": 642, "wins": 1, "last": "2024-07-16", "buyers": ["Directia Generala de Asistenta Sociala si Protectia Copilului Timis"], "value": 399133.83, "currency": "RON", "mixed": false, "url": "https://ted.europa.eu/en/notice/426769-2024"}, {"seller": "AMA FRUCT CP", "seller_country": "ROU", "seller_code": 642, "wins": 1, "last": "2024-07-15", "buyers": ["Directia Generala de Asistenta Sociala si Protectia Copilului Neamt"], "value": 5133829.12, "currency": "RON", "mixed": false, "url": "https://ted.europa.eu/en/notice/422348-2024"}, {"seller": "SARMATA Michał Dębski", "seller_country": "POL", "seller_code": 616, "wins": 1, "last": "2024-07-10", "buyers": ["ZAKŁAD KARNY W KAMIŃSKU"], "value": 289390.0, "currency": "PLN", "mixed": false, "url": "https://ted.europa.eu/en/notice/456592-2024"}]