[{"seller": "SANROTEX TRADING SRL", "seller_country": "ROU", "seller_code": 642, "wins": 7, "last": "2024-11-29", "buyers": ["SPITALUL CLINIC DE URGENTA PENTRU COPII ,,Maria Sklodowska Curie\"", "SPITAL CLINIC JUDETEAN DE URGENTA ORADEA", "SPITAL CLINIC JUDETEAN DE URGENTA BIHOR", "SPITALUL JUDETEAN DE URGENTA BACAU"], "value": 18657599.44, "currency": "RON", "mixed": false, "url": "https://ted.europa.eu/en/notice/730524-2024"}, {"seller": "CRIO - 2 S.R.L.", "seller_country": "ROU", "seller_code": 642, "wins": 3, "last": "2024-11-20", "buyers": ["SPITALUL JUDETEAN DE URGENTA VALCEA", "SPITALUL JUDETEAN DE URGENTA BACAU", "Spitalul Judetan de Urgenta \"Mavromati\" Botosani"], "value": 93853490.45, "currency": "RON", "mixed": false, "url": "https://ted.europa.eu/en/notice/708196-2024"}, {"seller": "CO&CO Consumer 2002 S.R.L.", "seller_country": "ROU", "seller_code": 642, "wins": 2, "last": "2024-12-16", "buyers": ["SPITALUL JUDETEAN DE URGENTA VALCEA"], "value": 3236280.9, "currency": "RON", "mixed": false, "url": "https://ted.europa.eu/en/notice/767718-2024"}, {"seller": "ALLIANCE HEALTHCARE ROMANIA", "seller_country": "ROU", "seller_code": 642, "wins": 2, "last": "2024-11-15", "buyers": ["SPITALUL JUDETEAN DE URGENTA VALCEA"], "value": 2530666.06, "currency": "RON", "mixed": false, "url": "https://ted.europa.eu/en/notice/696164-2024"}, {"seller": "MEGACONS-BRILLAGO", "seller_country": "ROU", "seller_code": 642, "wins": 2, "last": "2024-11-04", "buyers": ["Spitalul Clinic de Pneumoftiziologie Victor Babes Craiova", "SPITAL CLINIC JUDETEAN DE URGENTA ORADEA"], "value": 3574112.29, "currency": "RON", "mixed": false, "url": "https://ted.europa.eu/en/notice/667073-2024"}, {"seller": "VALDOMEDICA TRADING", "seller_country": "ROU", "seller_code": 642, "wins": 2, "last": "2024-10-08", "buyers": ["SPITALUL JUDETEAN DE URGENTA VALCEA"], "value": 2699029.48, "currency": "RON", "mixed": false, "url": "https://ted.europa.eu/en/notice/604149-2024"}, {"seller": "Lohmann & Rauscher Polska spółka z o.o.", "seller_country": "POL", "seller_code": 616, "wins": 2, "last": "2024-07-17", "buyers": ["Krakowski Szpital Specjalistyczny im. św. Jana Pawła II"], "value": 3365060.33, "currency": "PLN", "mixed": false, "url": "https://ted.europa.eu/en/notice/532102-2024"}, {"seller": "VETRO DESIGN", "seller_country": "ROU", "seller_code": 642, "wins": 1, "last": "2024-12-12", "buyers": ["SPITALUL JUDETEAN DE URGENTA VALCEA"], "value": 1341176.03, "currency": "RON", "mixed": false, "url": "https://ted.europa.eu/en/notice/761096-2024"}, {"seller": "CRAD RO", "seller_country": "ROU", "seller_code": 642, "wins": 1, "last": "2024-12-10", "buyers": ["SPITALUL JUDETEAN DE URGENTA BACAU"], "value": 401653.5, "currency": "RON", "mixed": false, "url": "https://ted.europa.eu/en/notice/753499-2024"}, {"seller": "SC CARTO PLAST SRL", "seller_country": "ROU", "seller_code": 642, "wins": 1, "last": "2024-12-06", "buyers": ["SPITALUL JUDETEAN DE URGENTA VALCEA"], "value": 1705172.45, "currency": "RON", "mixed": false, "url": "https://ted.europa.eu/en/notice/747228-2024"}, {"seller": "HS MEDICAL SRL", "seller_country": "ROU", "seller_code": 642, "wins": 1, "last": "2024-11-29", "buyers": ["Spitalul Judetan de Urgenta \"Mavromati\" Botosani"], "value": 12391682.29, "currency": "RON", "mixed": false, "url": "https://ted.europa.eu/en/notice/731522-2024"}, {"seller": "Limas Group S.R.L.", "seller_country": "ROU", "seller_code": 642, "wins": 1, "last": "2024-11-28", "buyers": ["Spitalul Universitar de Urgenta Militar Central \"Dr. Carol Davila\""], "value": 3625800.0, "currency": "RON", "mixed": false, "url": "https://ted.europa.eu/en/notice/725139-2024"}, {"seller": "STERIL ROMANIA", "seller_country": "ROU", "seller_code": 642, "wins": 1, "last": "2024-11-22", "buyers": ["Institutul Regional de Oncologie Iasi"], "value": 27309610.0, "currency": "RON", "mixed": false, "url": "https://ted.europa.eu/en/notice/715365-2024"}, {"seller": "DEMOPHORIUS HEALTHCARE", "seller_country": "ROU", "seller_code": 642, "wins": 1, "last": "2024-11-19", "buyers": ["SPITALUL JUDETEAN DE URGENTA VALCEA"], "value": 1328151.03, "currency": "RON", "mixed": false, "url": "https://ted.europa.eu/en/notice/705732-2024"}, {"seller": "EVOREVO", "seller_country": "ROU", "seller_code": 642, "wins": 1, "last": "2024-11-14", "buyers": ["SPITALUL JUDETEAN DE URGENTA VALCEA"], "value": 1584071.45, "currency": "RON", "mixed": false, "url": "https://ted.europa.eu/en/notice/695461-2024"}, {"seller": "LUAN VISION SRL", "seller_country": "ROU", "seller_code": 642, "wins": 1, "last": "2024-11-13", "buyers": ["Institutul Regional de Oncologie Iasi"], "value": 26671020.0, "currency": "RON", "mixed": false, "url": "https://ted.europa.eu/en/notice/692171-2024"}, {"seller": "STRYKER ROMANIA", "seller_country": "ROU", "seller_code": 642, "wins": 1, "last": "2024-11-04", "buyers": ["Spitalul Judetan de Urgenta \"Mavromati\" Botosani"], "value": 11899765.09, "currency": "RON", "mixed": false, "url": "https://ted.europa.eu/en/notice/668384-2024"}, {"seller": "ZARYS INTERNATIONAL GROUP MEDICAL EQUIPMENT S.R.L.", "seller_country": "ROU", "seller_code": 642, "wins": 1, "last": "2024-10-29", "buyers": ["Spitalul Municipal Campina"], "value": 1991873.88, "currency": "RON", "mixed": false, "url": "https://ted.europa.eu/en/notice/655869-2024"}, {"seller": "ZARYS International Group Sp. z o. o. Sp. k.", "seller_country": "POL", "seller_code": 616, "wins": 1, "last": "2024-10-11", "buyers": ["Samodzielny Publiczny Wojewódzki Szpital Zespolony w Szczecinie"], "value": 3333803.4, "currency": "PLN", "mixed": false, "url": "https://ted.europa.eu/en/notice/678993-2024"}, {"seller": "NANO BIO MEDICAL S.R.L.", "seller_country": "ROU", "seller_code": 642, "wins": 1, "last": "2024-10-10", "buyers": ["SPITALUL JUDETEAN DE URGENTA VALCEA"], "value": 1571421.45, "currency": "RON", "mixed": false, "url": "https://ted.europa.eu/en/notice/610888-2024"}, {"seller": "Lohmann & Rauscher Polska Sp. z o.o.", "seller_country": "POL", "seller_code": 616, "wins": 1, "last": "2024-10-09", "buyers": ["Krakowski Szpital Specjalistyczny im. św. Jana Pawła II"], "value": 2203605.42, "currency": "PLN", "mixed": false, "url": "https://ted.europa.eu/en/notice/607010-2024"}, {"seller": "DASCO DISTRIBUTION CONCEPT", "seller_country": "ROU", "seller_code": 642, "wins": 1, "last": "2024-10-08", "buyers": ["SPITALUL JUDETEAN DE URGENTA BACAU"], "value": 398394.5, "currency": "RON", "mixed": false, "url": "https://ted.europa.eu/en/notice/604979-2024"}, {"seller": "CARDION s.r.o.", "seller_country": "CZE", "seller_code": 203, "wins": 1, "last": "2024-09-27", "buyers": ["Nemocnice Na Homolce"], "value": 762200.0, "currency": "CZK", "mixed": false, "url": "https://ted.europa.eu/en/notice/642103-2024"}, {"seller": "BLACK STORM s.r.o.", "seller_country": "CZE", "seller_code": 203, "wins": 1, "last": "2024-09-27", "buyers": ["Nemocnice Na Homolce"], "value": 288349.75, "currency": "CZK", "mixed": false, "url": "https://ted.europa.eu/en/notice/630802-2024"}, {"seller": "MEDICAL GRUP", "seller_country": "ROU", "seller_code": 642, "wins": 1, "last": "2024-09-09", "buyers": ["Spitalul Clinic de Pneumoftiziologie Victor Babes Craiova"], "value": 265010.0, "currency": "RON", "mixed": false, "url": "https://ted.europa.eu/en/notice/540135-2024"}, {"seller": "Intra-Med Sp. z o.o.", "seller_country": "POL", "seller_code": 616, "wins": 1, "last": "2024-09-05", "buyers": ["Wojewódzki Szpital Specjalistyczny w Białej Podlaskiej"], "value": 558579.5, "currency": "PLN", "mixed": false, "url": "https://ted.europa.eu/en/notice/628533-2024"}, {"seller": "NOVA FIT 2000 SRL", "seller_country": "ROU", "seller_code": 642, "wins": 1, "last": "2024-09-05", "buyers": ["SPITALUL JUDETEAN DE URGENTA VALCEA"], "value": 1245116.03, "currency": "RON", "mixed": false, "url": "https://ted.europa.eu/en/notice/534113-2024"}, {"seller": "ALPHA MEDICAL S.R.L.", "seller_country": "ROU", "seller_code": 642, "wins": 1, "last": "2024-08-30", "buyers": ["SPITALUL JUDETEAN DE URGENTA VALCEA"], "value": 1392869.15, "currency": "RON", "mixed": false, "url": "https://ted.europa.eu/en/notice/521444-2024"}, {"seller": "LUAN VISION", "seller_country": "ROU", "seller_code": 642, "wins": 1, "last": "2024-08-08", "buyers": ["SPITALUL JUDETEAN DE URGENTA \"SF. PANTELIMON\" FOCSANI"], "value": 1382280.8, "currency": "RON", "mixed": false, "url": "https://ted.europa.eu/en/notice/479531-2024"}, {"seller": "Perfect Distribution a.s.", "seller_country": "CZE", "seller_code": 203, "wins": 1, "last": "2024-08-02", "buyers": ["Fakultní nemocnice Olomouc"], "value": 4148000.0, "currency": "CZK", "mixed": false, "url": "https://ted.europa.eu/en/notice/511472-2024"}, {"seller": "DELUXE MEDICRAFTS", "seller_country": "ROU", "seller_code": 642, "wins": 1, "last": "2024-08-02", "buyers": ["SPITALUL JUDETEAN DE URGENTA BACAU"], "value": 373392.5, "currency": "RON", "mixed": false, "url": "https://ted.europa.eu/en/notice/465815-2024"}, {"seller": "PAUL HARTMANN POLSKA Sp. z o. o.", "seller_country": "POL", "seller_code": 616, "wins": 1, "last": "2024-07-31", "buyers": ["Samodzielny Publiczny Zakład Opieki Zdrowotnej Wojewódzki Szpital Specjalistyczny Nr 3 w Rybniku"], "value": 1357654.7, "currency": "PLN", "mixed": false, "url": "https://ted.europa.eu/en/notice/621965-2024"}, {"seller": "NOVA FIT 2000", "seller_country": "ROU", "seller_code": 642, "wins": 1, "last": "2024-07-31", "buyers": ["Spitalul Clinic de Pneumoftiziologie Victor Babes Craiova"], "value": 7170579.4, "currency": "RON", "mixed": false, "url": "https://ted.europa.eu/en/notice/460625-2024"}, {"seller": "BIZMED", "seller_country": "ROU", "seller_code": 642, "wins": 1, "last": "2024-07-30", "buyers": ["SPITAL CLINIC JUDETEAN DE URGENTA ORADEA"], "value": 3167569.44, "currency": "RON", "mixed": false, "url": "https://ted.europa.eu/en/notice/455902-2024"}, {"seller": "INVIBIO CONSULTING", "seller_country": "ROU", "seller_code": 642, "wins": 1, "last": "2024-07-29", "buyers": ["Spitalul Judetan de Urgenta \"Mavromati\" Botosani"], "value": 11119617.91, "currency": "RON", "mixed": false, "url": "https://ted.europa.eu/en/notice/454874-2024"}, {"seller": "PAUL HARTMANN", "seller_country": "ROU", "seller_code": 642, "wins": 1, "last": "2024-07-18", "buyers": ["SPITAL CLINIC JUDETEAN DE URGENTA ORADEA"], "value": 3151114.94, "currency": "RON", "mixed": false, "url": "https://ted.europa.eu/en/notice/432741-2024"}, {"seller": "RUBICON EDITECH 89 S.R.L.", "seller_country": "ROU", "seller_code": 642, "wins": 1, "last": "2024-07-17", "buyers": ["SPITAL CLINIC JUDETEAN DE URGENTA BIHOR"], "value": 320125.8, "currency": "RON", "mixed": false, "url": "https://ted.europa.eu/en/notice/429257-2024"}, {"seller": "HEMA.T MEDICAL", "seller_country": "FRA", "seller_code": 251, "wins": 1, "last": "2024-07-10", "buyers": ["Etablissement Français du Sang Auvergne Rhône Alpes"], "value": 150000.0, "currency": "EUR", "mixed": false, "url": "https://ted.europa.eu/en/notice/478542-2024"}]