[{"seller": "Viešoji įstaiga Nacionalinis kraujo centras", "seller_country": "LTU", "seller_code": 440, "wins": 5, "last": "2026-05-22", "buyers": ["Lietuvos sveikatos mokslų universiteto ligoninė Kauno klinikos (PV)", "Kretingos rajono savivaldybės administracija", "Viešoji įstaiga CPO LT", "VšĮ Respublikinė Vilniaus universitetinė ligoninė (PV)"], "value": 5058635.0, "currency": "EUR", "mixed": false, "url": "https://ted.europa.eu/en/notice/353642-2026"}, {"seller": "VšĮ Vilniaus universiteto ligoninė Santaros klinikos", "seller_country": "LTU", "seller_code": 440, "wins": 4, "last": "2026-04-08", "buyers": ["VšĮ Respublikinė Vilniaus universitetinė ligoninė", "VšĮ Respublikinė Vilniaus universitetinė ligoninė (PV)"], "value": 218670.30000000002, "currency": "EUR", "mixed": false, "url": "https://ted.europa.eu/en/notice/236990-2026"}, {"seller": "DRK-Blutspendedienst West gGmbH", "seller_country": "DEU", "seller_code": 276, "wins": 1, "last": "2025-12-05", "buyers": ["Klinikum Lippe GmbH"], "value": 460700.0, "currency": "EUR", "mixed": false, "url": "https://ted.europa.eu/en/notice/850360-2025"}, {"seller": "DRK-Blutspendedienst-West GgmbH", "seller_country": "DEU", "seller_code": 276, "wins": 1, "last": "2025-12-04", "buyers": ["Berufsgenossenschaftliches Universitätsklinikum Bergmannsheil gGmbH"], "value": 1.0, "currency": "EUR", "mixed": false, "url": "https://ted.europa.eu/en/notice/805659-2025"}, {"seller": "Institut für Transfusionsmedizin Suhl gGmbH", "seller_country": "DEU", "seller_code": 276, "wins": 1, "last": "2025-07-17", "buyers": ["Klinikum der Stadt Ludwigshafen am Rhein gGmbH"], "value": 0.01, "currency": "EUR", "mixed": false, "url": "https://ted.europa.eu/en/notice/482995-2025"}, {"seller": "Regionalne Centrum Krwiodawstwa i Krwiolecznictwa", "seller_country": "POL", "seller_code": 616, "wins": 1, "last": "2025-01-14", "buyers": ["Szpital Joannitas w Pszczynie samorządowa spółka z o.o. w restrukturyzacji"], "value": 1669092.0, "currency": "PLN", "mixed": false, "url": "https://ted.europa.eu/en/notice/25358-2025"}, {"seller": "Universitätsklinikum Leipzig, Institut für Transfusionsmedizin", "seller_country": "DEU", "seller_code": 276, "wins": 1, "last": "2025-01-10", "buyers": ["Fraunhofer Gesellschaft e.V."], "value": 570768.64, "currency": "EUR", "mixed": false, "url": "https://ted.europa.eu/en/notice/49237-2025"}, {"seller": "VšĮ Nacionalinis kraujo centras", "seller_country": "LTU", "seller_code": 440, "wins": 1, "last": "2024-08-20", "buyers": ["Viešoji įstaiga CPO LT"], "value": 1913716.0, "currency": "EUR", "mixed": false, "url": "https://ted.europa.eu/en/notice/498377-2024"}, {"seller": "DRK-Blutspendedienst-West gGmbH", "seller_country": "DEU", "seller_code": 276, "wins": 1, "last": "2024-07-26", "buyers": ["Universitätsklinikum des Saarlandes"], "value": 0.1, "currency": "EUR", "mixed": false, "url": "https://ted.europa.eu/en/notice/452831-2024"}]